weather_server/__init__.py
weather_server/server.py
weather_server-1.0.0.dist-info/METADATA
weather_server-1.0.0.dist-info/WHEEL
weather_server-1.0.0.dist-info/top_level.txt
weather_server-1.0.0.dist-info/RECORD
